{
  "schema": {
    "type": "object",
    "properties": {
      "_userInvalidMessage": {
        "type": "string",
        "required": true
      },
      "nin": {
        "type": "string",
        "format": "ssn",
        "required": true,
        "minLength": 11,
        "maxLength": 11
      },
      "firstName": {
        "type": "string",
        "required": true
      },
      "lastName": {
        "type": "string",
        "required": true
      }
    }
  },


  "form": [
    {
      "type": "customer",
      "items": [
        {
          "itemType": "personNumber",
          "key": "nin",
          "title": "Fødselsnummer",
          "infoMessage": "'Fødselsnummer oppgis med 11 siffer",
          "placeholder": "Fill in your ssn"
        },
        {
          "itemType": "firstName",
          "key": "firstName",
          "title": "Fornavn",
          "validationMessage": "Vennligst fyll inn ditt fornavn",
          "infoMessage": "Vi anbefaler at du oppretter avtalegiro. Dette kan du enkelt gjøre når du betaler første faktura i din nettbank",
          "placeholder": "Fornavn"
        },
        {
          "itemType": "lastName",
          "key": "lastName",
          "title": "Etternavn",
          "validationMessage": "Vennligst fyll inn ditt etternavn",
          "infoMessage": "Vi anbefaler at du oppretter avtalegiro. Dette kan du enkelt gjøre når du betaler første faktura i din nettbank",
          "placeholder": "Etternavn"
        },
        {
          "itemType": "userError",
          "key": "_userInvalidMessage",
          "validationMessage": "Vi har sjekket navnet ditt mot våre systemer, og ikke funnet treff i skrivemåte. Årsaken til dette kan være tegn som bindestrek, dobbel konsonanter (f.eks. Normann/Norman), K eller C (f.eks. Monica/Monika) eller utelatelse/tilføring av et mellomnavn uten at dette er registert i våre systemer. Har du fremdeles problemer, ta kontakt med kundeservice på telefon 08880 eller e-post skadeforsikring@storebrand.no.",
          "type": "hidden"
        }
      ]
    }
  ]
}